ratelimitex/__init__.py
ratelimitex/client.py
ratelimitex/core.py
ratelimitex/decorators.py
ratelimitex/exceptions.py
ratelimitex/models.py
ratelimitex/py.typed
ratelimitex/utils.py
ratelimitex-0.1.0.dist-info/LICENSE
ratelimitex-0.1.0.dist-info/METADATA
ratelimitex-0.1.0.dist-info/WHEEL
ratelimitex-0.1.0.dist-info/RECORD
