Metadata-Version: 2.1
Name: ratelimitex
Version: 0.1.0
Summary: Enhanced rate limiter with multiple strategies and monitoring capabilities
License: MIT
Author: Nexrion Team
Requires-Python: >=3.9
Classifier: License :: OSI Approved :: MIT License
Classifier: Programming Language :: Python :: 3
Classifier: Programming Language :: Python :: 3.9
Classifier: Programming Language :: Python :: 3.10
Classifier: Programming Language :: Python :: 3.11
Classifier: Programming Language :: Python :: 3.12
Classifier: Programming Language :: Python :: 3 :: Only
Classifier: Typing :: Typed
Requires-Dist: pydantic (>=2.0,<3.0)
Project-URL: Bug Tracker, https://github.com/Nexrion/ratelimitex/issues
Project-URL: Homepage, https://github.com/Nexrion/ratelimitex
